{
  "msg": "success",
  "code": 0,
  "data": {
    "activityShowName": "抢购",
    "goods": [{
      "weight": 0,
      "bgGoodsId": 336,
      "collegeId": 1181,
      "remark": "长治",
      "unit": "类",
      "imageUrl": "http://upload.imxiaomai.com/upload2Qiniu/visit_img?id=154561&imageView2/0/w/300/h/300",
      "detailImageUrl": "http://upload.imxiaomai.com/upload2Qiniu/visit_img?id=154561&imageView2/0/w/450/h/450",
      "iconImageUrl": "http://upload.imxiaomai.com/upload2Qiniu/visit_img?id=154561&imageView2/0/w/150/h/150",
      "maxNum": 1,
      "saleSpec": "类",
      "originPlace": "越南",
      "goodsType": 1,
      "goodsStatus": 2,
      "goodsStatusDisplay": 3,
      "isDel": 0,
      "sourceType": 2,
      "distributeTypeDisplay": ["29分钟达", ""],
      "minWapPrice": 100,
      "maxWapPrice": 100,
      "minAppPrice": 100,
      "maxAppPrice": 100,
      "goodsPropertyList": [],
      "skuGoodsPropertyList": [],
      "tagChange": 0,
      "priceChange": 0,
      "available": 0,
      "activityGoodsId": 272,
      "activityBgGoodsId": 45,
      "activityGoodsName": "长治",
      "activityGoodsSubname": "",
      "activityId": 91,
      "activityGoodsDesc": "长治",
      "isSeckill": 0,
      "beginTime": 1444617300000,
      "endTime": 1444617900000,
      "showTime": 1443691800000,
      "skuList": [{
        "weight": 0,
        "bgSkuId": 303,
        "collegeId": 1181,
        "originPrice": 500,
        "stock": 0,
        "imageUrl": null,
        "skuType": 1,
        "distributeType": 1,
        "distributeTypeDesc": "29分钟达",
        "isDel": 0,
        "skuPropertyList": [],
        "numInCart": 0,
        "skuPropertyValueIdList": null,
        "activitySkuId": 290,
        "activityBgSkuId": 51,
        "activityGoodsId": 272,
        "activityPrice": 100
      }],
      "buyLeftTime": -97656,
      "buyLeftTimeShow": "<i>-27</i>时<i>-7</i>分<i>-36</i>秒",
      "timeBeforeStart": -98256,
      "timeBeforeStartShow": "<i>-27</i>时<i>-17</i>分<i>-36</i>秒",
      "buyEndTimeShow": "<i>0</i>时<i>10</i>分<i>0</i>秒",
      "killStarted": 2
    }, {
      "weight": 0,
      "bgGoodsId": 585,
      "collegeId": 1181,
      "remark": "山西",
      "unit": "瓶",
      "imageUrl": "http://upload.imxiaomai.com/upload2Qiniu/visit_img?id=159250&imageView2/0/w/300/h/300",
      "detailImageUrl": "http://upload.imxiaomai.com/upload2Qiniu/visit_img?id=159250&imageView2/0/w/450/h/450",
      "iconImageUrl": "http://upload.imxiaomai.com/upload2Qiniu/visit_img?id=159250&imageView2/0/w/150/h/150",
      "maxNum": 1,
      "saleSpec": "瓶",
      "originPlace": "山西",
      "goodsType": 1,
      "goodsStatus": 2,
      "goodsStatusDisplay": 5,
      "isDel": 0,
      "sourceType": 2,
      "distributeTypeDisplay": ["29分钟达", ""],
      "minWapPrice": 200,
      "maxWapPrice": 200,
      "minAppPrice": 200,
      "maxAppPrice": 200,
      "goodsPropertyList": [],
      "skuGoodsPropertyList": [],
      "tagChange": 0,
      "priceChange": 0,
      "available": 0,
      "activityGoodsId": 5245,
      "activityBgGoodsId": 291,
      "activityGoodsName": "益达",
      "activityGoodsSubname": "",
      "activityId": 91,
      "activityGoodsDesc": "山西",
      "isSeckill": 0,
      "beginTime": 1444297500000,
      "endTime": 1451554200000,
      "showTime": 1443691800000,
      "skuList": [{
        "weight": 0,
        "bgSkuId": 531,
        "collegeId": 1181,
        "originPrice": 500,
        "stock": 0,
        "imageUrl": "http://upload.imxiaomai.com/upload2Qiniu/visit_img?id=159250",
        "skuType": 1,
        "distributeType": 1,
        "distributeTypeDesc": "29分钟达",
        "isDel": 0,
        "skuPropertyList": [],
        "numInCart": 0,
        "skuPropertyValueIdList": null,
        "activitySkuId": 6894,
        "activityBgSkuId": 398,
        "activityGoodsId": 5245,
        "activityPrice": 200
      }],
      "buyLeftTime": 6838643,
      "buyLeftTimeShow": "<i>1899</i>时<i>37</i>分<i>23</i>秒",
      "timeBeforeStart": -418056,
      "timeBeforeStartShow": "<i>-116</i>时<i>-7</i>分<i>-36</i>秒",
      "buyEndTimeShow": "<i>2015</i>时<i>45</i>分<i>0</i>秒",
      "killStarted": 1
    }, {
      "weight": 0,
      "bgGoodsId": 373,
      "collegeId": 1181,
      "remark": "申购单",
      "unit": "返回",
      "imageUrl": "http://upload.imxiaomai.com/upload2Qiniu/visit_img?id=154633&imageView2/0/w/300/h/300",
      "detailImageUrl": "http://upload.imxiaomai.com/upload2Qiniu/visit_img?id=154633&imageView2/0/w/450/h/450",
      "iconImageUrl": "http://upload.imxiaomai.com/upload2Qiniu/visit_img?id=154633&imageView2/0/w/150/h/150",
      "maxNum": 1,
      "saleSpec": "特惠",
      "originPlace": "毛里求斯",
      "goodsType": 1,
      "goodsStatus": 2,
      "goodsStatusDisplay": 5,
      "isDel": 0,
      "sourceType": 2,
      "distributeTypeDisplay": ["29分钟达", ""],
      "minWapPrice": 100,
      "maxWapPrice": 100,
      "minAppPrice": 100,
      "maxAppPrice": 100,
      "goodsPropertyList": [],
      "skuGoodsPropertyList": [],
      "tagChange": 0,
      "priceChange": 0,
      "available": 0,
      "activityGoodsId": 5386,
      "activityBgGoodsId": 307,
      "activityGoodsName": "通达",
      "activityGoodsSubname": "",
      "activityId": 91,
      "activityGoodsDesc": "萨芬",
      "isSeckill": 0,
      "beginTime": 1444297500000,
      "endTime": 1451554200000,
      "showTime": 1443691800000,
      "skuList": [{
        "weight": 0,
        "bgSkuId": 338,
        "collegeId": 1181,
        "originPrice": 100,
        "stock": 0,
        "imageUrl": "http://upload.imxiaomai.com/upload2Qiniu/visit_img?id=154633",
        "skuType": 1,
        "distributeType": 1,
        "distributeTypeDesc": "29分钟达",
        "isDel": 0,
        "skuPropertyList": [],
        "numInCart": 0,
        "skuPropertyValueIdList": null,
        "activitySkuId": 7059,
        "activityBgSkuId": 414,
        "activityGoodsId": 5386,
        "activityPrice": 100
      }],
      "buyLeftTime": 6838643,
      "buyLeftTimeShow": "<i>1899</i>时<i>37</i>分<i>23</i>秒",
      "timeBeforeStart": -418056,
      "timeBeforeStartShow": "<i>-116</i>时<i>-7</i>分<i>-36</i>秒",
      "buyEndTimeShow": "<i>2015</i>时<i>45</i>分<i>0</i>秒",
      "killStarted": 1
    }, {
      "weight": 0,
      "bgGoodsId": 631,
      "collegeId": 1181,
      "remark": "埃塞俄比亚",
      "unit": "单号",
      "imageUrl": "http://upload.imxiaomai.com/upload2Qiniu/visit_img?id=164064&imageView2/0/w/300/h/300",
      "detailImageUrl": "http://upload.imxiaomai.com/upload2Qiniu/visit_img?id=164064&imageView2/0/w/450/h/450",
      "iconImageUrl": "http://upload.imxiaomai.com/upload2Qiniu/visit_img?id=164064&imageView2/0/w/150/h/150",
      "maxNum": 1,
      "saleSpec": "儿童和让他换",
      "originPlace": "老挝",
      "goodsType": 1,
      "goodsStatus": 2,
      "goodsStatusDisplay": 5,
      "isDel": 0,
      "sourceType": 2,
      "distributeTypeDisplay": ["29分钟达", ""],
      "minWapPrice": 1,
      "maxWapPrice": 1,
      "minAppPrice": 1,
      "maxAppPrice": 1,
      "goodsPropertyList": [],
      "skuGoodsPropertyList": [],
      "tagChange": 0,
      "priceChange": 0,
      "available": 0,
      "activityGoodsId": 5504,
      "activityBgGoodsId": 330,
      "activityGoodsName": "洋芋5",
      "activityGoodsSubname": "",
      "activityId": 91,
      "activityGoodsDesc": "埃塞俄比亚",
      "isSeckill": 0,
      "beginTime": 1444297500000,
      "endTime": 1451554200000,
      "showTime": 1443691800000,
      "skuList": [{
        "weight": 0,
        "bgSkuId": 567,
        "collegeId": 1181,
        "originPrice": 100,
        "stock": 0,
        "imageUrl": "http://upload.imxiaomai.com/upload2Qiniu/visit_img?id=165379",
        "skuType": 1,
        "distributeType": 1,
        "distributeTypeDesc": "29分钟达",
        "isDel": 0,
        "skuPropertyList": [],
        "numInCart": 0,
        "skuPropertyValueIdList": null,
        "activitySkuId": 7177,
        "activityBgSkuId": 437,
        "activityGoodsId": 5504,
        "activityPrice": 1
      }],
      "buyLeftTime": 6838643,
      "buyLeftTimeShow": "<i>1899</i>时<i>37</i>分<i>23</i>秒",
      "timeBeforeStart": -418056,
      "timeBeforeStartShow": "<i>-116</i>时<i>-7</i>分<i>-36</i>秒",
      "buyEndTimeShow": "<i>2015</i>时<i>45</i>分<i>0</i>秒",
      "killStarted": 1
    }, {
      "weight": 0,
      "bgGoodsId": 622,
      "collegeId": 1181,
      "remark": "埃塞俄比亚",
      "unit": "瓶",
      "imageUrl": "http://upload.imxiaomai.com/upload2Qiniu/visit_img?id=164047&imageView2/0/w/300/h/300",
      "detailImageUrl": "http://upload.imxiaomai.com/upload2Qiniu/visit_img?id=164047&imageView2/0/w/450/h/450",
      "iconImageUrl": "http://upload.imxiaomai.com/upload2Qiniu/visit_img?id=164047&imageView2/0/w/150/h/150",
      "maxNum": 1,
      "saleSpec": "瓶装",
      "originPlace": "埃塞俄比亚",
      "goodsType": 1,
      "goodsStatus": 2,
      "goodsStatusDisplay": 5,
      "isDel": 0,
      "sourceType": 2,
      "distributeTypeDisplay": ["29分钟达", ""],
      "minWapPrice": 1,
      "maxWapPrice": 1,
      "minAppPrice": 1,
      "maxAppPrice": 1,
      "goodsPropertyList": [],
      "skuGoodsPropertyList": [],
      "tagChange": 0,
      "priceChange": 0,
      "available": 0,
      "activityGoodsId": 5540,
      "activityBgGoodsId": 336,
      "activityGoodsName": "清至6",
      "activityGoodsSubname": "",
      "activityId": 91,
      "activityGoodsDesc": "埃塞俄比亚",
      "isSeckill": 0,
      "beginTime": 1444297500000,
      "endTime": 1451554200000,
      "showTime": 1443691800000,
      "skuList": [{
        "weight": 0,
        "bgSkuId": 558,
        "collegeId": 1181,
        "originPrice": 100,
        "stock": 0,
        "imageUrl": "http://upload.imxiaomai.com/upload2Qiniu/visit_img?id=164047",
        "skuType": 1,
        "distributeType": 1,
        "distributeTypeDesc": "29分钟达",
        "isDel": 0,
        "skuPropertyList": [],
        "numInCart": 0,
        "skuPropertyValueIdList": null,
        "activitySkuId": 7213,
        "activityBgSkuId": 443,
        "activityGoodsId": 5540,
        "activityPrice": 1
      }],
      "buyLeftTime": 6838643,
      "buyLeftTimeShow": "<i>1899</i>时<i>37</i>分<i>23</i>秒",
      "timeBeforeStart": -418056,
      "timeBeforeStartShow": "<i>-116</i>时<i>-7</i>分<i>-36</i>秒",
      "buyEndTimeShow": "<i>2015</i>时<i>45</i>分<i>0</i>秒",
      "killStarted": 1
    }, {
      "weight": 0,
      "bgGoodsId": 623,
      "collegeId": 1181,
      "remark": "埃塞俄比亚",
      "unit": "瓶",
      "imageUrl": "http://upload.imxiaomai.com/upload2Qiniu/visit_img?id=164048&imageView2/0/w/300/h/300",
      "detailImageUrl": "http://upload.imxiaomai.com/upload2Qiniu/visit_img?id=164048&imageView2/0/w/450/h/450",
      "iconImageUrl": "http://upload.imxiaomai.com/upload2Qiniu/visit_img?id=164048&imageView2/0/w/150/h/150",
      "maxNum": 1,
      "saleSpec": "瓶装",
      "originPlace": "埃塞俄比亚",
      "goodsType": 1,
      "goodsStatus": 2,
      "goodsStatusDisplay": 5,
      "isDel": 0,
      "sourceType": 2,
      "distributeTypeDisplay": ["29分钟达", ""],
      "minWapPrice": 1,
      "maxWapPrice": 1,
      "minAppPrice": 1,
      "maxAppPrice": 1,
      "goodsPropertyList": [],
      "skuGoodsPropertyList": [],
      "tagChange": 0,
      "priceChange": 0,
      "available": 0,
      "activityGoodsId": 5534,
      "activityBgGoodsId": 335,
      "activityGoodsName": "清至7",
      "activityGoodsSubname": "",
      "activityId": 91,
      "activityGoodsDesc": "埃塞俄比亚",
      "isSeckill": 0,
      "beginTime": 1444297500000,
      "endTime": 1451554200000,
      "showTime": 1443691800000,
      "skuList": [{
        "weight": 0,
        "bgSkuId": 559,
        "collegeId": 1181,
        "originPrice": 100,
        "stock": 0,
        "imageUrl": "http://upload.imxiaomai.com/upload2Qiniu/visit_img?id=164048",
        "skuType": 1,
        "distributeType": 1,
        "distributeTypeDesc": "29分钟达",
        "isDel": 0,
        "skuPropertyList": [],
        "numInCart": 0,
        "skuPropertyValueIdList": null,
        "activitySkuId": 7207,
        "activityBgSkuId": 442,
        "activityGoodsId": 5534,
        "activityPrice": 1
      }],
      "buyLeftTime": 6838643,
      "buyLeftTimeShow": "<i>1899</i>时<i>37</i>分<i>23</i>秒",
      "timeBeforeStart": -418056,
      "timeBeforeStartShow": "<i>-116</i>时<i>-7</i>分<i>-36</i>秒",
      "buyEndTimeShow": "<i>2015</i>时<i>45</i>分<i>0</i>秒",
      "killStarted": 1
    }, {
      "weight": 0,
      "bgGoodsId": 624,
      "collegeId": 1181,
      "remark": "埃塞俄比亚",
      "unit": "瓶",
      "imageUrl": "http://upload.imxiaomai.com/upload2Qiniu/visit_img?id=164049&imageView2/0/w/300/h/300",
      "detailImageUrl": "http://upload.imxiaomai.com/upload2Qiniu/visit_img?id=164049&imageView2/0/w/450/h/450",
      "iconImageUrl": "http://upload.imxiaomai.com/upload2Qiniu/visit_img?id=164049&imageView2/0/w/150/h/150",
      "maxNum": 1,
      "saleSpec": "瓶装",
      "originPlace": "埃塞俄比亚",
      "goodsType": 1,
      "goodsStatus": 2,
      "goodsStatusDisplay": 5,
      "isDel": 0,
      "sourceType": 2,
      "distributeTypeDisplay": ["29分钟达", ""],
      "minWapPrice": 1,
      "maxWapPrice": 1,
      "minAppPrice": 1,
      "maxAppPrice": 1,
      "goodsPropertyList": [],
      "skuGoodsPropertyList": [],
      "tagChange": 0,
      "priceChange": 0,
      "available": 0,
      "activityGoodsId": 5528,
      "activityBgGoodsId": 334,
      "activityGoodsName": "清至8",
      "activityGoodsSubname": "",
      "activityId": 91,
      "activityGoodsDesc": "埃塞俄比亚",
      "isSeckill": 0,
      "beginTime": 1444297500000,
      "endTime": 1451554200000,
      "showTime": 1443691800000,
      "skuList": [{
        "weight": 0,
        "bgSkuId": 560,
        "collegeId": 1181,
        "originPrice": 100,
        "stock": 0,
        "imageUrl": "http://upload.imxiaomai.com/upload2Qiniu/visit_img?id=164049",
        "skuType": 1,
        "distributeType": 1,
        "distributeTypeDesc": "29分钟达",
        "isDel": 0,
        "skuPropertyList": [],
        "numInCart": 0,
        "skuPropertyValueIdList": null,
        "activitySkuId": 7201,
        "activityBgSkuId": 441,
        "activityGoodsId": 5528,
        "activityPrice": 1
      }],
      "buyLeftTime": 6838643,
      "buyLeftTimeShow": "<i>1899</i>时<i>37</i>分<i>23</i>秒",
      "timeBeforeStart": -418056,
      "timeBeforeStartShow": "<i>-116</i>时<i>-7</i>分<i>-36</i>秒",
      "buyEndTimeShow": "<i>2015</i>时<i>45</i>分<i>0</i>秒",
      "killStarted": 1
    }, {
      "weight": 0,
      "bgGoodsId": 625,
      "collegeId": 1181,
      "remark": "埃塞俄比亚",
      "unit": "瓶",
      "imageUrl": "http://upload.imxiaomai.com/upload2Qiniu/visit_img?id=164054&imageView2/0/w/300/h/300",
      "detailImageUrl": "http://upload.imxiaomai.com/upload2Qiniu/visit_img?id=164054&imageView2/0/w/450/h/450",
      "iconImageUrl": "http://upload.imxiaomai.com/upload2Qiniu/visit_img?id=164054&imageView2/0/w/150/h/150",
      "maxNum": 1,
      "saleSpec": "瓶装",
      "originPlace": "埃塞俄比亚",
      "goodsType": 1,
      "goodsStatus": 2,
      "goodsStatusDisplay": 5,
      "isDel": 0,
      "sourceType": 2,
      "distributeTypeDisplay": ["29分钟达", ""],
      "minWapPrice": 1,
      "maxWapPrice": 1,
      "minAppPrice": 1,
      "maxAppPrice": 1,
      "goodsPropertyList": [],
      "skuGoodsPropertyList": [],
      "tagChange": 0,
      "priceChange": 0,
      "available": 0,
      "activityGoodsId": 5522,
      "activityBgGoodsId": 333,
      "activityGoodsName": "清至9",
      "activityGoodsSubname": "",
      "activityId": 91,
      "activityGoodsDesc": "埃塞俄比亚",
      "isSeckill": 0,
      "beginTime": 1444297500000,
      "endTime": 1451554200000,
      "showTime": 1443691800000,
      "skuList": [{
        "weight": 0,
        "bgSkuId": 561,
        "collegeId": 1181,
        "originPrice": 100,
        "stock": 0,
        "imageUrl": "http://upload.imxiaomai.com/upload2Qiniu/visit_img?id=164054",
        "skuType": 1,
        "distributeType": 1,
        "distributeTypeDesc": "29分钟达",
        "isDel": 0,
        "skuPropertyList": [],
        "numInCart": 0,
        "skuPropertyValueIdList": null,
        "activitySkuId": 7195,
        "activityBgSkuId": 440,
        "activityGoodsId": 5522,
        "activityPrice": 1
      }],
      "buyLeftTime": 6838643,
      "buyLeftTimeShow": "<i>1899</i>时<i>37</i>分<i>23</i>秒",
      "timeBeforeStart": -418056,
      "timeBeforeStartShow": "<i>-116</i>时<i>-7</i>分<i>-36</i>秒",
      "buyEndTimeShow": "<i>2015</i>时<i>45</i>分<i>0</i>秒",
      "killStarted": 1
    }, {
      "weight": 0,
      "bgGoodsId": 626,
      "collegeId": 1181,
      "remark": "埃塞俄比亚",
      "unit": "瓶",
      "imageUrl": "http://upload.imxiaomai.com/upload2Qiniu/visit_img?id=164055&imageView2/0/w/300/h/300",
      "detailImageUrl": "http://upload.imxiaomai.com/upload2Qiniu/visit_img?id=164055&imageView2/0/w/450/h/450",
      "iconImageUrl": "http://upload.imxiaomai.com/upload2Qiniu/visit_img?id=164055&imageView2/0/w/150/h/150",
      "maxNum": 1,
      "saleSpec": "瓶装",
      "originPlace": "埃塞俄比亚",
      "goodsType": 1,
      "goodsStatus": 2,
      "goodsStatusDisplay": 5,
      "isDel": 0,
      "sourceType": 2,
      "distributeTypeDisplay": ["29分钟达", ""],
      "minWapPrice": 1,
      "maxWapPrice": 1,
      "minAppPrice": 1,
      "maxAppPrice": 1,
      "goodsPropertyList": [],
      "skuGoodsPropertyList": [],
      "tagChange": 0,
      "priceChange": 0,
      "available": 0,
      "activityGoodsId": 5516,
      "activityBgGoodsId": 332,
      "activityGoodsName": "清至10",
      "activityGoodsSubname": "",
      "activityId": 91,
      "activityGoodsDesc": "埃塞俄比亚",
      "isSeckill": 0,
      "beginTime": 1444297500000,
      "endTime": 1451554200000,
      "showTime": 1443691800000,
      "skuList": [{
        "weight": 0,
        "bgSkuId": 562,
        "collegeId": 1181,
        "originPrice": 100,
        "stock": 0,
        "imageUrl": "http://upload.imxiaomai.com/upload2Qiniu/visit_img?id=164055",
        "skuType": 1,
        "distributeType": 1,
        "distributeTypeDesc": "29分钟达",
        "isDel": 0,
        "skuPropertyList": [],
        "numInCart": 0,
        "skuPropertyValueIdList": null,
        "activitySkuId": 7189,
        "activityBgSkuId": 439,
        "activityGoodsId": 5516,
        "activityPrice": 1
      }],
      "buyLeftTime": 6838643,
      "buyLeftTimeShow": "<i>1899</i>时<i>37</i>分<i>23</i>秒",
      "timeBeforeStart": -418056,
      "timeBeforeStartShow": "<i>-116</i>时<i>-7</i>分<i>-36</i>秒",
      "buyEndTimeShow": "<i>2015</i>时<i>45</i>分<i>0</i>秒",
      "killStarted": 1
    }, {
      "weight": 0,
      "bgGoodsId": 630,
      "collegeId": 1181,
      "remark": "埃塞俄比亚",
      "unit": "单号",
      "imageUrl": "http://upload.imxiaomai.com/upload2Qiniu/visit_img?id=164063&imageView2/0/w/300/h/300",
      "detailImageUrl": "http://upload.imxiaomai.com/upload2Qiniu/visit_img?id=164063&imageView2/0/w/450/h/450",
      "iconImageUrl": "http://upload.imxiaomai.com/upload2Qiniu/visit_img?id=164063&imageView2/0/w/150/h/150",
      "maxNum": 1,
      "saleSpec": "儿童和让他换",
      "originPlace": "老挝",
      "goodsType": 1,
      "goodsStatus": 2,
      "goodsStatusDisplay": 5,
      "isDel": 0,
      "sourceType": 2,
      "distributeTypeDisplay": ["29分钟达", ""],
      "minWapPrice": 1,
      "maxWapPrice": 1,
      "minAppPrice": 1,
      "maxAppPrice": 1,
      "goodsPropertyList": [],
      "skuGoodsPropertyList": [],
      "tagChange": 0,
      "priceChange": 0,
      "available": 0,
      "activityGoodsId": 5510,
      "activityBgGoodsId": 331,
      "activityGoodsName": "洋芋3",
      "activityGoodsSubname": "",
      "activityId": 91,
      "activityGoodsDesc": "埃塞俄比亚",
      "isSeckill": 0,
      "beginTime": 1444297500000,
      "endTime": 1451554200000,
      "showTime": 1443691800000,
      "skuList": [{
        "weight": 0,
        "bgSkuId": 566,
        "collegeId": 1181,
        "originPrice": 100,
        "stock": 0,
        "imageUrl": "http://upload.imxiaomai.com/upload2Qiniu/visit_img?id=164063",
        "skuType": 1,
        "distributeType": 1,
        "distributeTypeDesc": "29分钟达",
        "isDel": 0,
        "skuPropertyList": [],
        "numInCart": 0,
        "skuPropertyValueIdList": null,
        "activitySkuId": 7183,
        "activityBgSkuId": 438,
        "activityGoodsId": 5510,
        "activityPrice": 1
      }],
      "buyLeftTime": 6838643,
      "buyLeftTimeShow": "<i>1899</i>时<i>37</i>分<i>23</i>秒",
      "timeBeforeStart": -418056,
      "timeBeforeStartShow": "<i>-116</i>时<i>-7</i>分<i>-36</i>秒",
      "buyEndTimeShow": "<i>2015</i>时<i>45</i>分<i>0</i>秒",
      "killStarted": 1
    }],
    "paginationInfo": {
      "currentPage": 1,
      "recordPerPage": 10,
      "totalPage": 5,
      "totalRecord": 47,
      "limit": 10,
      "offset": 0
    }
  },
  "serverTime": "2015-10-13 13:52:36"
}
