{
  "msg": "",
  "code": 0,
  "data": {
    "order": {
      "orderId": 425734,
      "userId": 123456982,
      "collegeId": 1,
      "collegeName": "小麦总部",
      "receiverName": "郭超",
      "receiverPhone": "18612244032",
      "totalPay": 3911,
      "onlinePay": 4112,
      "onlinePayId": "",
      "onlinePayType": 1,
      "couponId": 0,
      "couponPay": 0,
      "firstSub": 0,
      "fullSub": 0,
      "freight": 201,
      "freightSub": 0,
      "fillPay": 0,
      "orderCode": "XM00100425734",
      "remark": "",
      "status": 4,
      "device": 1,
      "createTime": 1446645334000,
      "updateTime": 1446645348000,
      "payTime": 1446645348000,
      "childOrderList": [{
        "childOrderId": 425735,
        "orderId": 425734,
        "userId": 123456982,
        "collegeId": 1,
        "collegeName": null,
        "receiverName": "郭超",
        "receiverPhone": "18612244032",
        "totalPay": 4,
        "freight": 0,
        "freightSub": 0,
        "orderCode": "XM00100425734",
        "childOrderCode": "XM00300425735",
        "remark": "我随便写点东西",
        "distributeType": 1,
        "status": 1,
        "deliveryType": 1,
        "ldcFixBeginTime": null,
        "ldcFixEndTime": null,
        "deliveryBeginTime": 1446649200000,
        "deliveryEndTime": 1446650100000,
        "deliveryAddress": "学一",
        "selfPickUpTime": null,
        "selfPickUpAddress": "",
        "createTime": 1446645334000,
        "updateTime": 1446645348000,
        "childOrderDetailList": [{
          "childOrderDetailId": 191,
          "orderId": 425734,
          "childOrderId": 425735,
          "userId": 123456982,
          "collegeId": 1,
          "goodsId": 7359,
          "bgSkuId": 463,
          "skuId": 12224,
          "skuName": "App-普通商品8",
          "skuSubName": "",
          "skuNum": 2,
          "skuOriginPrice": 100,
          "skuPrice": 2,
          "status": 1,
          "createTime": 1446645334000,
          "updateTime": null,
          "storageId": 794387644,
          "distributeType": 1,
          "sourceType": 1,
          "imageUrl": "http://upload.imxiaomai.com/upload2Qiniu/visit_img?id=157515",
          "categoryId": 58,
          "ratio": 0,
          "propertyIds": "null",
          "wmsGoodsIds": ""
        }],
        "deliverCompanyCode": null,
        "deliverSheetCode": null,
        "deliverCompanyName": null,
        "deliveryInfo": null,
        "storageName": null,
        "storageId": 794387644,
        "h5DeliveryPageUrl": null,
        "deliveryTimeStr": null,
        "deliveryTimeType": 0
      }, {
        "deliveryAddress": "小麦总部第三方商品营业厅",
        "freight": 201,
        "freightSub": 0,
        "distributeType": 2,
        "th3ChildOrderList": [{
          "childOrderId": 425736,
          "orderId": 425734,
          "userId": 123456982,
          "collegeId": 1,
          "collegeName": null,
          "receiverName": "郭超",
          "receiverPhone": "18612244032",
          "totalPay": 7,
          "freight": 1,
          "freightSub": 0,
          "orderCode": "XM00100425734",
          "childOrderCode": "XM00500425736",
          "remark": "",
          "distributeType": 2,
          "status": 1,
          "deliveryType": 0,
          "ldcFixBeginTime": null,
          "ldcFixEndTime": null,
          "deliveryBeginTime": null,
          "deliveryEndTime": null,
          "deliveryAddress": "小麦总部第三方商品营业厅",
          "selfPickUpTime": null,
          "selfPickUpAddress": "",
          "createTime": 1446645334000,
          "updateTime": 1446645348000,
          "childOrderDetailList": [{
            "childOrderDetailId": 192,
            "orderId": 425734,
            "childOrderId": 425736,
            "userId": 123456982,
            "collegeId": 1,
            "goodsId": 13281,
            "bgSkuId": 592,
            "skuId": 20340,
            "skuName": "海飞丝洗发水",
            "skuSubName": "",
            "skuNum": 1,
            "skuOriginPrice": 7800,
            "skuPrice": 3,
            "status": 1,
            "createTime": 1446645334000,
            "updateTime": null,
            "storageId": 794387662,
            "distributeType": 2,
            "sourceType": 1,
            "imageUrl": "http://upload.imxiaomai.com/upload2Qiniu/visit_img?id=167351",
            "categoryId": 76,
            "ratio": 0,
            "propertyIds": "null",
            "wmsGoodsIds": ""
          }, {
            "childOrderDetailId": 193,
            "orderId": 425734,
            "childOrderId": 425736,
            "userId": 123456982,
            "collegeId": 1,
            "goodsId": 13334,
            "bgSkuId": 593,
            "skuId": 20393,
            "skuName": "多芬洗发水",
            "skuSubName": "",
            "skuNum": 1,
            "skuOriginPrice": 300,
            "skuPrice": 1,
            "status": 1,
            "createTime": 1446645334000,
            "updateTime": null,
            "storageId": 794387662,
            "distributeType": 2,
            "sourceType": 1,
            "imageUrl": "http://upload.imxiaomai.com/upload2Qiniu/visit_img?id=167375",
            "categoryId": 76,
            "ratio": 0,
            "propertyIds": "null",
            "wmsGoodsIds": ""
          }, {
            "childOrderDetailId": 194,
            "orderId": 425734,
            "childOrderId": 425736,
            "userId": 123456982,
            "collegeId": 1,
            "goodsId": 14285,
            "bgSkuId": 599,
            "skuId": 21404,
            "skuName": "多芬洗发乳",
            "skuSubName": "",
            "skuNum": 1,
            "skuOriginPrice": 300,
            "skuPrice": 1,
            "status": 1,
            "createTime": 1446645334000,
            "updateTime": null,
            "storageId": 794387662,
            "distributeType": 2,
            "sourceType": 1,
            "imageUrl": "http://upload.imxiaomai.com/upload2Qiniu/visit_img?id=167446",
            "categoryId": 76,
            "ratio": 0,
            "propertyIds": "null",
            "wmsGoodsIds": ""
          }, {
            "childOrderDetailId": 195,
            "orderId": 425734,
            "childOrderId": 425736,
            "userId": 123456982,
            "collegeId": 1,
            "goodsId": 14827,
            "bgSkuId": 619,
            "skuId": 22125,
            "skuName": "飘柔洗发水",
            "skuSubName": "",
            "skuNum": 1,
            "skuOriginPrice": 300,
            "skuPrice": 1,
            "status": 1,
            "createTime": 1446645334000,
            "updateTime": null,
            "storageId": 794387662,
            "distributeType": 2,
            "sourceType": 1,
            "imageUrl": "http://upload.imxiaomai.com/upload2Qiniu/visit_img?id=167708",
            "categoryId": 76,
            "ratio": 0,
            "propertyIds": "null",
            "wmsGoodsIds": ""
          }, {
            "childOrderDetailId": 196,
            "orderId": 425734,
            "childOrderId": 425736,
            "userId": 123456982,
            "collegeId": 1,
            "goodsId": 14852,
            "bgSkuId": 620,
            "skuId": 22150,
            "skuName": "力士洗发水",
            "skuSubName": "",
            "skuNum": 1,
            "skuOriginPrice": 300,
            "skuPrice": 1,
            "status": 1,
            "createTime": 1446645334000,
            "updateTime": null,
            "storageId": 794387662,
            "distributeType": 2,
            "sourceType": 1,
            "imageUrl": "http://upload.imxiaomai.com/upload2Qiniu/visit_img?id=167710",
            "categoryId": 76,
            "ratio": 0,
            "propertyIds": "null",
            "wmsGoodsIds": ""
          }],
          "deliverCompanyCode": null,
          "deliverSheetCode": null,
          "deliverCompanyName": null,
          "deliveryInfo": null,
          "storageName": "聚美优品2号仓",
          "storageId": 794387662,
          "h5DeliveryPageUrl": null,
          "deliveryTimeStr": null,
          "deliveryTimeType": 0
        }, {
          "childOrderId": 425737,
          "orderId": 425734,
          "userId": 123456982,
          "collegeId": 1,
          "collegeName": null,
          "receiverName": "郭超",
          "receiverPhone": "18612244032",
          "totalPay": 3900,
          "freight": 200,
          "freightSub": 0,
          "orderCode": "XM00100425734",
          "childOrderCode": "XM00500425737",
          "remark": "",
          "distributeType": 2,
          "status": 1,
          "deliveryType": 0,
          "ldcFixBeginTime": null,
          "ldcFixEndTime": null,
          "deliveryBeginTime": null,
          "deliveryEndTime": null,
          "deliveryAddress": "小麦总部第三方商品营业厅",
          "selfPickUpTime": null,
          "selfPickUpAddress": "",
          "createTime": 1446645334000,
          "updateTime": 1446645348000,
          "childOrderDetailList": [{
            "childOrderDetailId": 197,
            "orderId": 425734,
            "childOrderId": 425737,
            "userId": 123456982,
            "collegeId": 1,
            "goodsId": 15182,
            "bgSkuId": 626,
            "skuId": 22495,
            "skuName": "11.11秒杀商品_机器人",
            "skuSubName": "",
            "skuNum": 2,
            "skuOriginPrice": 199900,
            "skuPrice": 150,
            "status": 1,
            "createTime": 1446645334000,
            "updateTime": null,
            "storageId": 39,
            "distributeType": 2,
            "sourceType": 1,
            "imageUrl": "http://upload.imxiaomai.com/upload2Qiniu/visit_img?id=169243",
            "categoryId": 76,
            "ratio": 0,
            "propertyIds": "null",
            "wmsGoodsIds": ""
          }, {
            "childOrderDetailId": 198,
            "orderId": 425734,
            "childOrderId": 425737,
            "userId": 123456982,
            "collegeId": 1,
            "goodsId": 15201,
            "bgSkuId": 627,
            "skuId": 22514,
            "skuName": "11.11秒杀商品_机器猫",
            "skuSubName": "",
            "skuNum": 3,
            "skuOriginPrice": 1200,
            "skuPrice": 1200,
            "status": 1,
            "createTime": 1446645334000,
            "updateTime": null,
            "storageId": 39,
            "distributeType": 2,
            "sourceType": 1,
            "imageUrl": "http://upload.imxiaomai.com/upload2Qiniu/visit_img?id=169255",
            "categoryId": 76,
            "ratio": 0,
            "propertyIds": "null",
            "wmsGoodsIds": ""
          }],
          "deliverCompanyCode": null,
          "deliverSheetCode": null,
          "deliverCompanyName": null,
          "deliveryInfo": null,
          "storageName": "天猫店",
          "storageId": 39,
          "h5DeliveryPageUrl": null,
          "deliveryTimeStr": null,
          "deliveryTimeType": 0
        }]
      }],
      "categoryIdList": [{
        "58": 4,
        "76": 3907
      }]
    }
  },
  "serverTime": "2015-11-04 21:55:49"
}
